hanser/__init__.py
hanser/calc.py
hanser_module_upload-0.0.1.dist-info/LICENSE
hanser_module_upload-0.0.1.dist-info/METADATA
hanser_module_upload-0.0.1.dist-info/WHEEL
hanser_module_upload-0.0.1.dist-info/top_level.txt
hanser_module_upload-0.0.1.dist-info/RECORD
