Metadata-Version: 2.1
Name: hanser-module-upload
Version: 0.0.1
Summary: 简单的加减运算上传测试
Home-page: https://www.baidu.com
Author: 布诺妮亚
Author-email: hanser@baka.com
License: UNKNOWN
Platform: UNKNOWN
Classifier: Programming Language :: Python :: 3
Classifier: License :: OSI Approved :: MIT License
Classifier: Operating System :: OS Independent
